kidotest/__init__.py
kidotest/decorators.py
kidotest/models.py
kidotest/compat.py
django_kidotest-1.1.dist-info/top_level.txt
django_kidotest-1.1.dist-info/METADATA
django_kidotest-1.1.dist-info/DESCRIPTION.rst
django_kidotest-1.1.dist-info/metadata.json
django_kidotest-1.1.dist-info/WHEEL
django_kidotest-1.1.dist-info/RECORD
