Metadata-Version: 2.0
Name: django-kidotest
Version: 1.1
Summary: Code snippets which help writing automated tests for Django.
Home-page: http://kidosoft.pl
Author: Jakub STOLARSKI (Dryobates)
Author-email: jakub.stolarski@kidosoft.pl
License: beerware
Keywords: django testing
Platform: UNKNOWN
Classifier: Development Status :: 4 - Beta
Classifier: Environment :: Web Environment
Classifier: Intended Audience :: Developers
Classifier: License :: OSI Approved :: BSD License
Classifier: Operating System :: OS Independent
Classifier: Framework :: Django
Classifier: Programming Language :: Python
Classifier: Topic :: Utilities
Requires-Dist: mock
